{"Subject":{"2":"Animal Science and Zoology","10":"General Medicine","30":"General Veterinary","17":"Food Science","1":"Food Animals","35":"Ecology","39":" Evolution","40":" Behavior and Systematics","20":"Genetics","5":"General Biochemistry","6":" Genetics and Molecular Biology","81":"Small Animals","29":"Biotechnology","34":"Endocrinology","7":"Biochemistry","4":"General Agricultural and Biological Sciences","25":"Plant Science","21":"Pharmacology","47":"Toxicology","3":"General Chemistry","46":"Microbiology","145":"Agronomy and Crop Science","65":"Infectious Diseases","8":"Molecular Biology","117":"Medical Laboratory Technology","101":"Immunology","86":"Cell Biology","108":"Environmental Chemistry","119":"Analytical Chemistry","36":"Nature and Landscape Conservation","38":"Bioengineering","105":"Experimental and Cognitive Psychology","121":"Parasitology","63":"Microbiology (medical)","28":"Multidisciplinary","91":"Developmental Biology","165":"General Immunology and Microbiology","106":"Insect Science","110":"Virology","64":"Pharmacology (medical)","74":"Physiology","203":"Applied Microbiology and Biotechnology","26":"Aquatic Science","56":"Organic Chemistry","113":"Public Health","114":" Environmental and Occupational Health","49":"Health","50":" Toxicology and Mutagenesis","163":"Clinical Biochemistry","22":"Pharmaceutical Science","32":"Molecular Medicine","130":"General Neuroscience","23":"Surgery","12":"Cancer Research","118":"Cardiology and Cardiovascular Medicine","61":"General Pharmacology","62":" Toxicology and Pharmaceutics","13":"Oncology","45":"Clinical Neurology","57":"Spectroscopy","33":"Drug Discovery","93":"History","59":"Computer Science Applications","107":"Pollution","82":"Biomedical Engineering","44":"Cellular and Molecular Neuroscience","97":"Psychiatry and Mental health","182":"Archaeology","148":"Sociology and Political Science","146":"Immunology and Allergy","51":"Physical and Theoretical Chemistry","54":"Radiology Nuclear Medicine and imaging","71":" Monitoring","72":" Policy and Law","70":"Management","216":"Agricultural and Biological Sciences (miscellaneous)","15":"Medicine (miscellaneous)","48":"Environmental Engineering","68":"Geography","99":"Genetics(clinical)","144":" Diabetes and Metabolism","69":" Planning and Development","55":"Inorganic Chemistry","80":"General Environmental Science","67":" Sustainability and the Environment","66":"Renewable Energy","52":"Waste Management and Disposal","124":"Behavioral Neuroscience","75":"Biophysics","169":"Nutrition and Dietetics","58":"Catalysis","128":"Pathology and Forensic Medicine","27":"Anthropology","89":"General Physics and Astronomy","96":"Neurology","156":"Orthopedics and Sports Medicine","127":" medical","112":"Cultural Studies","215":"Hematology","120":"Equine","157":"Education","152":"Nephrology","167":"Literature and Literary Theory","147":"Philosophy","41":"Economics and Econometrics","129":"Histology","161":"Biomaterials","109":"Physiology (medical)","205":"Pulmonary and Respiratory Medicine","79":"Industrial and Manufacturing Engineering","131":"Electrical and Electronic Engineering","136":"Cognitive Neuroscience","164":"Otorhinolaryngology","77":"General Chemical Engineering","90":"General Materials Science","88":"General Engineering","111":"Arts and Humanities (miscellaneous)","11":"Urology","53":"Epidemiology","140":"Pediatrics","60":"Forestry","102":"History and Philosophy of Science","94":"Gastroenterology","141":" Perinatology","142":" and Child Health","202":"Transplantation","135":"Law","125":"Ecological Modelling","31":"Complementary and alternative medicine","143":"Internal Medicine","37":"General Psychology","138":"Obstetrics and Gynaecology","137":"Neuropsychology and Physiological Psychology","116":"Instrumentation","73":"Earth-Surface Processes","166":"Biological Psychiatry","184":"Oral Surgery","237":"Anatomy","95":"Anesthesiology and Pain Medicine","126":"Water Science and Technology","173":"Applied Mathematics","168":"Visual Arts and Performing Arts","98":"General Dentistry","248":"Software","24":"Dermatology","153":"Ophthalmology","151":"Health Policy","175":"Clinical Psychology","78":"Strategy and Management","224":"Condensed Matter Physics","159":"Development","177":"Health(social science)","170":"Developmental Neuroscience","9":"Structural Biology","104":"Oceanography","18":"Critical Care and Intensive Care Medicine","19":"Emergency Medicine","160":"General Computer Science","181":"Endocrine and Autonomic Systems","87":"Ageing","155":"Religious studies","214":"Global and Planetary Change","233":"Computer Networks and Communications","133":" and Optics","230":"Linguistics and Language","232":"Language and Linguistics","139":"Reproductive Medicine","241":"Veterinary (miscalleneous)","179":"Soil Science","132":"Atomic and Molecular Physics","176":"Palaeontology","187":"Geology","272":"Statistics and Probability","234":"Radiological and Ultrasound Technology","178":" Toxicology and Pharmaceutics (miscellaneous)","149":"Social Psychology","100":"Colloid and Surface Chemistry","85":" Reliability and Quality","84":" Risk","158":"Geriatrics and Gerontology","83":"Safety","154":"Sensory Systems","134":"Rehabilitation","172":"Modelling and Simulation","242":"Physical Therapy","243":" Sports Therapy and Rehabilitation","219":"Electronic","220":" Optical and Magnetic Materials","162":"Materials Chemistry","258":"Developmental and Educational Psychology","269":"Horticulture","103":"Radiation","223":"Safety Research","228":"Polymers and Plastics","231":"Communication","206":"Mechanical Engineering","76":"Electrochemistry","190":"Surfaces and Interfaces","43":"Finance","257":"Process Chemistry and Technology","249":"Computational Theory and Mathematics","264":"General Earth and Planetary Sciences","16":"Neuroscience (miscellaneous)","239":"Energy Engineering and Power Technology","238":"Fuel Technology","229":"Acoustics and Ultrasonics","278":" ethics and legal aspects","92":"Organizational Behavior and Human Resource Management","225":"Metals and Alloys","277":"Issues","247":" Econometrics and Finance","246":"General Economics","271":" Probability and Uncertainty","267":"General Arts and Humanities","240":"Gerontology","270":"Statistics","236":"Hepatology","174":"Computational Mathematics","199":"General Nursing","208":"Mechanics of Materials","200":"General Social Sciences","180":"Theoretical Computer Science","204":"Rheumatology","122":"Political Science and International Relations","209":"Ceramics and Composites","212":"Tourism","213":" Leisure and Hospitality Management","191":"Management of Technology and Innovation","254":"Economics","253":"Music","252":"Business and International Management","251":"Marketing","42":"Accounting","185":"Periodontics","255":" Econometrics and Finance (miscellaneous)","193":"Social Sciences (miscellaneous)","273":"Atmospheric Science","262":"Ocean Engineering","171":"Artificial Intelligence","197":"Chemistry (miscellaneous)","217":"Applied Psychology","293":"Library and Information Sciences","201":"Environmental Science (miscellaneous)","280":"Leadership and Management","221":"Surfaces","222":" Coatings and Films","207":"Civil and Structural Engineering","260":"Hardware and Architecture","288":" Genetics and Molecular Biology (miscellaneous)","226":"Chemical Engineering (miscellaneous)","279":"Speech and Hearing","296":"Community and Home Care","263":"Research and Theory","290":"Museology","281":"Critical Care","183":"Orthodontics","14":"Immunology and Microbiology (miscellaneous) ","189":"Control and Systems Engineering","297":"Advanced and Specialised Nursing","259":"Nuclear Energy and Engineering","244":"Stratigraphy","211":"Emergency","123":"Public Administration","198":"General Mathematics","256":"Embryology","250":"General Decision Sciences","289":"Mathematical Physics","284":"Filtration and Separation","285":"Statistical and Nonlinear Physics","286":"Phychiatric Mental Health","287":"LPN and LVN","210":"Occupational Therapy","265":"Classics","282":"Building and Construction","291":"Automotive Engineering","292":"Transportation","227":"Materials Science (miscellaneous)","294":"Fundamentals and skills","295":"Geochemistry and Petrology","115":"Nuclear and High Energy Physics","283":"Geometry and Topology","235":"Human Factors and Ergonomics","266":"Nursing (miscellaneous)","261":"Information Systems","196":"Physics and Astronomy (miscellaneous)","188":"Architecture ","276":"Analysis","275":"Algebra and Number Theory","274":"Engineering (miscellaneous)","245":"Earth and Planetary Sciences (miscellaneous)","195":"Computer Science (miscellaneous)","194":"Oncology(nursing)","192":"Human-Computer Interaction","186":"Geotechnical Engineering and Engineering Geology","268":"Computational Mechanics","150":"Gender Studies","218":"General Energy"},"Count":{"2":3952,"10":1750,"30":1156,"17":1080,"1":968,"35":774,"39":589,"40":589,"20":519,"5":431,"6":431,"81":373,"29":326,"34":312,"7":294,"4":291,"25":256,"21":254,"47":253,"3":248,"46":216,"145":202,"65":201,"8":200,"117":183,"101":179,"86":161,"108":148,"119":137,"36":134,"38":122,"105":121,"121":113,"63":100,"28":99,"91":98,"165":86,"106":83,"110":78,"64":70,"74":70,"203":68,"26":65,"56":64,"113":61,"114":61,"49":59,"50":59,"163":58,"22":58,"32":56,"130":55,"23":54,"12":52,"118":51,"61":50,"62":50,"13":50,"45":50,"57":48,"33":47,"93":46,"59":46,"107":45,"82":44,"44":44,"97":42,"182":42,"148":41,"146":40,"51":40,"54":39,"71":38,"72":38,"70":38,"216":38,"15":38,"48":37,"68":37,"99":37,"144":37,"69":37,"55":36,"80":36,"67":35,"66":35,"52":35,"124":35,"75":33,"169":32,"58":32,"128":32,"27":31,"89":30,"96":29,"156":28,"127":27,"112":27,"215":27,"120":27,"157":26,"152":26,"167":26,"147":26,"41":26,"129":24,"161":23,"109":23,"205":21,"79":21,"131":20,"136":20,"164":20,"77":20,"90":20,"88":19,"111":19,"11":19,"53":18,"140":18,"60":17,"102":17,"94":17,"141":16,"142":16,"202":16,"135":16,"125":16,"31":16,"143":15,"37":15,"138":15,"137":15,"116":15,"73":15,"166":14,"184":14,"237":14,"95":12,"126":12,"173":12,"168":12,"98":12,"248":11,"24":11,"153":11,"151":11,"175":11,"78":11,"224":10,"159":9,"177":9,"170":9,"9":9,"104":9,"18":9,"19":9,"160":9,"181":9,"87":9,"155":9,"214":9,"233":9,"133":8,"230":8,"232":8,"139":8,"241":8,"179":8,"132":8,"176":7,"187":7,"272":7,"234":7,"178":7,"149":7,"100":7,"85":7,"84":7,"158":7,"83":7,"154":7,"134":7,"172":7,"242":6,"243":6,"219":6,"220":6,"162":6,"258":5,"269":5,"103":5,"223":5,"228":5,"231":5,"206":5,"76":5,"190":5,"43":5,"257":5,"249":5,"264":5,"16":5,"239":5,"238":4,"229":4,"278":4,"92":4,"225":4,"277":4,"247":4,"246":4,"271":4,"267":4,"240":4,"270":4,"236":4,"174":4,"199":4,"208":4,"200":4,"180":4,"204":4,"122":4,"209":4,"212":4,"213":4,"191":4,"254":3,"253":3,"252":3,"251":3,"42":3,"185":3,"255":3,"193":3,"273":3,"262":3,"171":3,"197":3,"217":3,"293":3,"201":3,"280":3,"221":3,"222":3,"207":3,"260":3,"288":3,"226":3,"279":2,"296":2,"263":2,"290":2,"281":2,"183":2,"14":2,"189":2,"297":2,"259":2,"244":2,"211":2,"123":2,"198":2,"256":2,"250":2,"289":1,"284":1,"285":1,"286":1,"287":1,"210":1,"265":1,"282":1,"291":1,"292":1,"227":1,"294":1,"295":1,"115":1,"283":1,"235":1,"266":1,"261":1,"196":1,"188":1,"276":1,"275":1,"274":1,"245":1,"195":1,"194":1,"192":1,"186":1,"268":1,"150":1,"218":1}}